flask_tml/__init__.py
flask_tml/tml.py
flask_tml/tml_cookies.py
flask_tml/translator.py
flask_tml-0.3.1.dist-info/DESCRIPTION.rst
flask_tml-0.3.1.dist-info/METADATA
flask_tml-0.3.1.dist-info/metadata.json
flask_tml-0.3.1.dist-info/RECORD
flask_tml-0.3.1.dist-info/top_level.txt
flask_tml-0.3.1.dist-info/WHEEL
